README.md
setup.py
eth_tool/__init__.py
eth_tool/block.py
eth_tool/chain.py
eth_tool/connector.py
eth_tool/db.py
eth_tool/functions.py
eth_tool/manager.py
eth_tools.egg-info/PKG-INFO
eth_tools.egg-info/SOURCES.txt
eth_tools.egg-info/dependency_links.txt
eth_tools.egg-info/requires.txt
eth_tools.egg-info/top_level.txt
test/__init__.py
test/env.py
test/test_chain.py
test/test_db.py
test/test_manager.py