Metadata-Version: 1.0
Name: eth-tools
Version: 0.0.1
Summary: like function listtransactions for bitcoin
Home-page: https://github.com/l3n641/eth_tool
Author: l3n641
Author-email: hh250@qq.com
License: MIT
Platform: any
